CONTRIBUTING.md
Dockerfile
LICENSE.md
MANIFEST.in
README-DEVELOPMENT.md
README.md
pyproject.toml
requirements.txt
setup.cfg
setup.py
eze/__init__.py
eze/__main__.py
eze/version.py
eze/cli/__init__.py
eze/cli/main.py
eze/cli/commands/__init__.py
eze/cli/commands/housekeeping_commands.py
eze/cli/commands/reporter_commands.py
eze/cli/commands/test_commands.py
eze/cli/commands/tool_commands.py
eze/core/__init__.py
eze/core/autoconfig.py
eze/core/config.py
eze/core/engine.py
eze/core/license.py
eze/core/reporter.py
eze/core/tool.py
eze/data/default_autoconfig.json
eze/data/license_data/spdx-license-list-data-supplement.json
eze/plugins/__init__.py
eze/plugins/base_plugins.py
eze/plugins/reporters/__init__.py
eze/plugins/reporters/bom.py
eze/plugins/reporters/console.py
eze/plugins/reporters/eze.py
eze/plugins/reporters/html.py
eze/plugins/reporters/json.py
eze/plugins/reporters/markdown.py
eze/plugins/reporters/sarif.py
eze/plugins/tools/__init__.py
eze/plugins/tools/anchore_grype.py
eze/plugins/tools/anchore_syft.py
eze/plugins/tools/checkmarx_kics.py
eze/plugins/tools/container_trivy.py
eze/plugins/tools/dotnet_cyclonedx.py
eze/plugins/tools/java_cyclonedx.py
eze/plugins/tools/node_cyclonedx.py
eze/plugins/tools/node_npmaudit.py
eze/plugins/tools/node_npmoutdated.py
eze/plugins/tools/python_bandit.py
eze/plugins/tools/python_cyclonedx.py
eze/plugins/tools/python_outdated.py
eze/plugins/tools/raw.py
eze/plugins/tools/semgrep.py
eze/plugins/tools/trufflehog.py
eze/utils/__init__.py
eze/utils/config.py
eze/utils/error.py
eze/utils/git.py
eze/utils/log.py
eze/utils/markdown_print.py
eze/utils/package.py
eze/utils/purl.py
eze/utils/scan_result.py
eze/utils/semvar.py
eze/utils/cli/__init__.py
eze/utils/cli/docker.py
eze/utils/cli/exe.py
eze/utils/cli/run.py
eze/utils/cli/version.py
eze/utils/cli/windowslex.py
eze/utils/click/__init__.py
eze/utils/click/command_helpers.py
eze/utils/data/__init__.py
eze/utils/data/cve.py
eze/utils/data/cvss.py
eze/utils/data/osv.py
eze_cli.egg-info/PKG-INFO
eze_cli.egg-info/SOURCES.txt
eze_cli.egg-info/dependency_links.txt
eze_cli.egg-info/entry_points.txt
eze_cli.egg-info/requires.txt
eze_cli.egg-info/top_level.txt