Metadata-Version: 2.1
Name: eze-cli
Version: 1.1.0
Summary: Eze the one stop cli for security testing
Home-page: https://github.com/RiverSafeUK/eze-cli
Author: RiverSafe,
Author-email: anthony.mckale@riversafe.co.uk,
License: "MIT license"
Project-URL: Homepage, https://github.com/RiverSafeUK/eze-cli
Project-URL: Source, https://github.com/RiverSafeUK/eze-cli
Keywords: eze,cli,eze-cli,security-testing,SCA,SAST,Secrets,Infrastructure-Scan
Classifier: Development Status :: 3 - Alpha
Classifier: Intended Audience :: Developers
Classifier: License :: OSI Approved :: MIT License
Classifier: Topic :: Software Development :: Testing
Classifier: Topic :: Security
Classifier: Topic :: Utilities
Classifier: Operating System :: OS Independent
Classifier: Programming Language :: Python
Classifier: Programming Language :: Python :: 3.7
Classifier: Programming Language :: Python :: 3.8
Classifier: Programming Language :: Python :: 3.9
Requires-Python: >=3.7
License-File: LICENSE.md
